missing_101703571/__init__.py
missing_101703571/missing_101703571.py
missing_101703571-0.0.1.dist-info/LICENSE.txt
missing_101703571-0.0.1.dist-info/METADATA
missing_101703571-0.0.1.dist-info/WHEEL
missing_101703571-0.0.1.dist-info/top_level.txt
missing_101703571-0.0.1.dist-info/RECORD
