Metadata-Version: 2.1
Name: missing-101703571
Version: 0.0.1
Summary: Python package for filling the missing values using mean(Statistical model)
Home-page: UNKNOWN
Author: Sunishka Jain
Author-email: sunishkajain15@gmail.com
License: UNKNOWN
Platform: UNKNOWN
Classifier: Programming Language :: Python :: 3
Classifier: License :: OSI Approved :: MIT License
Classifier: Operating System :: OS Independent
Requires-Python: >=3.6
